pgmq_sqlalchemy/__init__.py
pgmq_sqlalchemy/_types.py
pgmq_sqlalchemy/_utils.py
pgmq_sqlalchemy/operation.py
pgmq_sqlalchemy/queue.py
pgmq_sqlalchemy/schema.py
pgmq_sqlalchemy-0.2.0.dist-info/METADATA
pgmq_sqlalchemy-0.2.0.dist-info/WHEEL
pgmq_sqlalchemy-0.2.0.dist-info/licenses/LICENSE
pgmq_sqlalchemy-0.2.0.dist-info/RECORD
