Metadata-Version: 2.4
Name: pgmq-sqlalchemy
Version: 0.2.0
Summary: More flexible PGMQ Postgres extension Python client that using sqlalchemy ORM, supporting both async and sync engines, sessionmakers or built from dsn.
Project-URL: Homepage, https://github.com/jason810496/pgmq-sqlalchemy
Project-URL: Repository, https://github.com/jason810496/pgmq-sqlalchemy
Project-URL: Documentation, https://pgmq-sqlalchemy.readthedocs.io/en/latest/
Author-email: jason810496 <810496@email.wlsh.tyc.edu.tw>
License: MIT
License-File: LICENSE
Keywords: PGMQ,SQLAlchemy,pgmq,sqlalchemy,tembo_pgmq_python
Classifier: Intended Audience :: Developers
Classifier: Intended Audience :: Information Technology
Classifier: License :: OSI Approved :: MIT License
Classifier: Operating System :: MacOS
Classifier: Operating System :: Microsoft :: Windows
Classifier: Operating System :: POSIX
Classifier: Operating System :: Unix
Classifier: Programming Language :: Python :: 3
Classifier: Programming Language :: Python :: 3.9
Classifier: Programming Language :: Python :: 3.10
Classifier: Programming Language :: Python :: 3.11
Classifier: Programming Language :: Python :: 3.12
Requires-Python: >=3.9
Requires-Dist: sqlalchemy>=2.0.31
Provides-Extra: asyncpg
Requires-Dist: asyncpg>=0.29.0; extra == 'asyncpg'
Requires-Dist: greenlet>=3.0.3; extra == 'asyncpg'
Provides-Extra: pg8000
Requires-Dist: pg8000>=1.31.2; extra == 'pg8000'
Provides-Extra: psycopg
Requires-Dist: psycopg>=3.2.1; extra == 'psycopg'
Provides-Extra: psycopg2-binary
Requires-Dist: psycopg2-binary>=2.9.9; extra == 'psycopg2-binary'
Provides-Extra: psycopg2cffi
Requires-Dist: psycopg2cffi>=2.9.0; extra == 'psycopg2cffi'
